mafin/__init__.py
mafin/mafin.py
MAFin-0.9.dist-info/LICENSE.md
MAFin-0.9.dist-info/METADATA
MAFin-0.9.dist-info/WHEEL
MAFin-0.9.dist-info/entry_points.txt
MAFin-0.9.dist-info/top_level.txt
MAFin-0.9.dist-info/RECORD
