Metadata-Version: 2.1
Name: MAFin
Version: 0.9
Summary: Motif Detection in Multiple Alignment Files: CLI tool to process and analyze MAF files ( Multiple alignment format ) 
Home-page: https://github.com/Georgakopoulos-Soares-lab/MAFin
Author: Patsakis Michail , Provatas Kimon, Ilias Georgakopoulos Soares, Ioannis Mouratidis
Author-email: kap6605@psu.edu , mpp5977@psu.edu
Classifier: Programming Language :: Python :: 3
Classifier: License :: OSI Approved :: GNU General Public License v3 (GPLv3)
Classifier: Operating System :: OS Independent
Requires-Python: >=3.6
License-File: LICENSE.md
Requires-Dist: biopython
Requires-Dist: pyahocorasick
